sqlserverport/__init__.py
sqlserverport/sqlserverport.py
sqlserverport-1.0.1.dist-info/LICENSE
sqlserverport-1.0.1.dist-info/METADATA
sqlserverport-1.0.1.dist-info/WHEEL
sqlserverport-1.0.1.dist-info/top_level.txt
sqlserverport-1.0.1.dist-info/RECORD
