Metadata-Version: 2.1
Name: sqlserverport
Version: 1.0.1
Summary: Query SQL Browser for port used by named instance
Home-page: https://github.com/gordthompson/sqlserverport
Author: Gord Thompson
Author-email: gord@gordthompson.com
License: MIT
Project-URL: Documentation, https://github.com/gordthompson/sqlserverport/wiki
Project-URL: Source, https://github.com/gordthompson/sqlserverport
Project-URL: Tracker, https://github.com/gordthompson/sqlserverport/issues
Keywords: Microsoft SQL Server Linux
Platform: UNKNOWN
Classifier: Development Status :: 5 - Production/Stable
Classifier: Intended Audience :: Developers
Classifier: License :: OSI Approved :: MIT License
Classifier: Programming Language :: Python
Classifier: Programming Language :: Python :: 3
Classifier: Programming Language :: Python :: Implementation :: CPython
Classifier: Topic :: Database :: Front-Ends
Classifier: Operating System :: Unix
